zlayer/__init__.py
zlayer/py.typed
zlayer_sdk-0.1.0.dist-info/METADATA
zlayer_sdk-0.1.0.dist-info/WHEEL
zlayer_sdk-0.1.0.dist-info/RECORD
