Metadata-Version: 2.4
Name: zlayer-sdk
Version: 0.1.0
Summary: ZLayer Plugin Development Kit for Python
License-Expression: MIT
Keywords: plugin,wasi,wasm,zlayer
Classifier: Development Status :: 3 - Alpha
Classifier: Intended Audience :: Developers
Classifier: License :: OSI Approved :: MIT License
Classifier: Programming Language :: Python :: 3.11
Classifier: Programming Language :: Python :: 3.12
Classifier: Topic :: Software Development :: Libraries
Requires-Python: >=3.11
Provides-Extra: dev
Requires-Dist: componentize-py>=0.13; extra == 'dev'
Requires-Dist: mypy>=1.8; extra == 'dev'
Requires-Dist: pytest>=8.0; extra == 'dev'
Requires-Dist: ruff>=0.3; extra == 'dev'
